{"canonical_case_id":"IL-HOMICIDE-2025-RAHAT-MNDHR-ABU-BLL","incident_geography":"israel_arab_society","victim_name":"منذر أبو بلال","victim_name_ar":"منذر أبو بلال","victim_name_he":null,"victim_name_en":null,"aliases":[],"name_transliterations":[{"value":"מנד'ר אבו בלאל","target_script":"he","source_script":"ar","method":"dictionary","source_value":"منذر أبو بلال"},{"value":"Manadahar Abu Balal","target_script":"en","source_script":"ar","method":"dictionary","source_value":"منذر أبو بلال"}],"victim_age":null,"victim_gender":"M","victim_profession":null,"victim_residence":null,"death_date":null,"incident_date":"2025-05-22","incident_date_possible":null,"incident_time":null,"city":"رهط","city_normalized":{"name_ar":"رهط","name_he":"רהט","name_en":"Rahat","district":"Southern","lat":31.395,"lng":34.7561},"neighborhood":null,"exact_place_type":null,"district":"Southern District","region":null,"hospital":null,"weapon_type":"firearm","weapon_subtype":null,"num_victims":1,"suspect_name":null,"suspect_age":null,"suspect_relation":null,"suspect_profession":null,"suspect_profession_conflict":[],"suspect_status":"at_large","legal_status":null,"police_investigation_status":null,"arrest_location":null,"police_status":null,"evidence":[],"media":[],"media_evidence":[{"media_id":"phash:fa0d0c72eb324d99","type":"crime_scene","status":"available","primary_url":"https://data.arab48.com/data/news/2025/05/26/20250526054057.jpg","mirror_urls":[],"source_article_urls":["https://www.arab48.com/محليات/أخبار-محلية/2025/05/26/النقب-وفاة-الشاب-منذر-أبو-بلال-متأثرا-بإصابته-بإطلاق-رصاص"],"caption":"من موقع الجريمة برهط","alt_text":null,"width":640,"height":376,"mime_type":null,"sha256":"bf1d88be12a67a43a145bcc5439cce8a5f46c9b870a9559ba50e53b974401323","phash":"fa0d0c72eb324d99","classifier_tier":"keyword","confidence":0.65,"classification_evidence":["keyword:crime_scene:موقع الجريمة","clip:crime_scene:0.25"],"is_stock_photo":false,"is_evidence":true,"evidence_reason":"category:crime_scene+city:رهط","appearance_count":1}],"victim_outcome":"died","motive":"family_dispute","organized_crime":null,"family_dispute":true,"community_context":null,"sources":[{"url":"https://www.arab48.com/محليات/أخبار-محلية/2025/05/26/النقب-وفاة-الشاب-منذر-أبو-بلال-متأثرا-بإصابته-بإطلاق-رصاص","discovery_source":"arab48","actual_publisher":"Arab48","source_name":"Arab48","language":"ar","published_at":"2025-05-26T17:42:46","confidence_score":0.9,"paywalled":false,"body_extracted":true}],"conflicts":{},"flags":["single_source","needs_tier_1","needs_tier_3"],"confidence":{"case_identity":0.75,"victim_identity":0.292,"timeline":0.333,"legal_status":0.25,"location_detail":0.333,"media":0.4},"confidence_score":0.423,"tier_coverage":{"tier_1":[],"tier_2":["Arab48"],"tier_3":[],"untiered":[]},"timeline":[{"date":"2025-05-22","event":"Incident occurred","confidence":"high"},{"date":"2025-05-26","event":"Reported in Arab48","confidence":"high","source_url":"https://www.arab48.com/محليات/أخبار-محلية/2025/05/26/النقب-وفاة-الشاب-منذر-أبو-بلال-متأثرا-بإصابته-بإطلاق-رصاص"}],"motive_translations":null,"arrest_location_translations":null,"dropped_invalid_sources":[],"rejected_unrelated_articles":[],"reconciliation_provenance":[],"case_narrative_ar":"توفي منذر أبو بلال من رهط متأثراً بإصابته بعيار ناري في 22 أيار/مايو 2025. استُهدف أبو بلال أثناء عودته من العمل في شاحنة. المشتبه بهم في إطلاق النار ما زالوا طلقاء.","case_narrative_he":"מנذر אבו בילאל מרהט נפטר ב-22 במאי 2025 מפצעיו מירי. אבו בילאל נורה כשחזר מעבודתו במשאית. החשודים בירי עדיין חופשיים.","case_narrative_en":"Munther Abu Bilal from Rahat died on May 22, 2025, from gunshot wounds. Abu Bilal was targeted while returning from work in a truck. The suspects in the shooting remain at large.","review_status":"auto","pipeline_run_id":"canonical_2025-01-01_2025-12-31","enrichment_passes":0,"_pipeline_run_id":"canonical_2025-01-01_2025-12-31","run_id":"canonical","case_index":228}