{"canonical_case_id":"IL-HOMICIDE-2026-HAIFA-SHYL-ABU-JBL","incident_geography":"israel_arab_society","victim_name":"سهيل أبو جبل","victim_name_ar":"سهيل أبو جبل","victim_name_he":"סוהיל אבו ג'בל","victim_name_en":null,"aliases":[],"name_transliterations":[{"value":"Sahayal Abu Jabal","target_script":"en","source_script":"ar","method":"dictionary","source_value":"سهيل أبو جبل"}],"victim_age":26,"victim_gender":"M","victim_profession":null,"victim_residence":null,"death_date":null,"incident_date":"2026-02-18","incident_date_possible":null,"incident_time":null,"city":"حيفا","city_normalized":{"name_ar":"حيفا","name_he":"חיפה","name_en":"Haifa","district":"Haifa","lat":32.794,"lng":34.9896},"neighborhood":null,"exact_place_type":null,"district":"Haifa District","region":null,"hospital":null,"weapon_type":"firearm","weapon_subtype":null,"num_victims":4,"suspect_name":null,"suspect_age":null,"suspect_relation":null,"suspect_profession":null,"suspect_profession_conflict":[],"suspect_status":"unknown","legal_status":null,"police_investigation_status":null,"arrest_location":null,"police_status":null,"evidence":[],"media":[{"media_id":"phash:d35b3f3f07874300","type":"crime_scene","status":"available","primary_url":"https://images.wcdn.co.il/f_auto,q_auto,w_1200,t_54/3/9/6/6/3966278-46.jpg","mirror_urls":[],"source_article_urls":["https://news.walla.co.il/item/3818250"],"caption":null,"alt_text":null,"width":1200,"height":673,"mime_type":null,"sha256":"0e860d985966582c383e0010216debd178966479ca678951c81c8ddb4381e8a3","phash":"d35b3f3f07874300","classifier_tier":"clip","confidence":0.3111799955368042,"classification_evidence":["keyword:no_text_signal","clip:crime_scene:0.31","gemini_skipped:budget_or_offline"],"is_stock_photo":false,"is_evidence":false,"evidence_reason":"og_image_lead:single_publisher_unverified","appearance_count":1},{"media_id":"phash:f8f40f7715858b0a","type":"other","status":"available","primary_url":"https://data.arab48.com/data/news/2026/02/18/20260218090340.jpg","mirror_urls":[],"source_article_urls":["https://www.arab48.com/محليات/أخبار-محلية/2026/02/18/إصابة-شاب-بجراح-حرجة-برصاص-الشرطة-في-كابول"],"caption":"من موقع جريمة القتل المزدوجة في مدينة حيفا","alt_text":null,"width":1600,"height":900,"mime_type":null,"sha256":"c4494d0c18dadaa6ea9cd0130bf3e17103b25dec7186668b6f9fad72e9de8faf","phash":"f8f40f7715858b0a","classifier_tier":"keyword","confidence":0.3,"classification_evidence":["keyword:no_match","clip:funeral:0.25","gemini_skipped:budget_or_offline"],"is_stock_photo":false,"is_evidence":false,"evidence_reason":"default:no_evidence_signal","appearance_count":1},{"media_id":"phash:ce9937e805db01f2","type":"suspect_portrait","status":"available","primary_url":"https://ynet-pic1.yit.co.il/picserver6/crop_images/2026/02/18/Skaa119m0011x/Skaa119m0011x_2_8_1279_721_0_large.jpg","mirror_urls":["https://ynet-pic1.yit.co.il/picserver6/crop_images/2026/02/18/Skaa119m0011x/Skaa119m0011x_2_22_1279_720_0_large.jpg"],"source_article_urls":["https://www.ynet.co.il/news/article/b1irgkxubx"],"caption":null,"alt_text":null,"width":490,"height":276,"mime_type":null,"sha256":"23c9c55be4924a25b0c141632b914b99ad03dd0985f2dfb8e302ab23697b5a38","phash":"ce9937e805db01f2","classifier_tier":"clip","confidence":0.241102397441864,"classification_evidence":["keyword:no_text_signal","clip:suspect_portrait:0.24","gemini_skipped:budget_or_offline"],"is_stock_photo":false,"is_evidence":false,"evidence_reason":"og_image_lead:single_publisher_unverified","appearance_count":1},{"media_id":"phash:f3324a3452fda253","type":"crime_scene","status":"available","primary_url":"https://ynet-pic1.yit.co.il/picserver6/crop_images/2026/02/18/SkguM4tXOZx/SkguM4tXOZx_0_0_1280_720_0_large.jpg","mirror_urls":[],"source_article_urls":["https://www.ynet.co.il/news/article/b1irgkxubx"],"caption":null,"alt_text":null,"width":490,"height":276,"mime_type":null,"sha256":"ccf63b1fb43fe34eea66afcf1ab2c3a289bbeebcdf1e5c552b0cc6281a6fc6ac","phash":"f3324a3452fda253","classifier_tier":"clip","confidence":0.22359085083007812,"classification_evidence":["keyword:no_text_signal","clip:crime_scene:0.22","gemini_skipped:budget_or_offline"],"is_stock_photo":false,"is_evidence":false,"evidence_reason":"default:no_evidence_signal","appearance_count":1},{"media_id":"phash:8d4d7264f077a067","type":"suspect_portrait","status":"available","primary_url":"https://ynet-pic1.yit.co.il/picserver6/crop_images/2026/02/18/Hyef9007OZl/Hyef9007OZl_0_0_615_346_0_large.jpg","mirror_urls":[],"source_article_urls":["https://www.ynet.co.il/news/article/b1irgkxubx"],"caption":null,"alt_text":null,"width":615,"height":346,"mime_type":null,"sha256":"d487dcfdbdcbd2d5c155ffd783054f5e6b904d0466dc711931ab798ef4db2f74","phash":"8d4d7264f077a067","classifier_tier":"clip","confidence":0.23770298063755035,"classification_evidence":["keyword:no_text_signal","clip:suspect_portrait:0.24","gemini_skipped:budget_or_offline"],"is_stock_photo":false,"is_evidence":false,"evidence_reason":"default:no_evidence_signal","appearance_count":1},{"media_id":"phash:e3c1847cec09f91b","type":"police_activity","status":"available","primary_url":"https://ynet-pic1.yit.co.il/picserver6/crop_images/2026/02/18/Bkg3y0Fmubg/Bkg3y0Fmubg_0_0_1280_943_0_large.jpg","mirror_urls":[],"source_article_urls":["https://www.ynet.co.il/news/article/b1irgkxubx"],"caption":null,"alt_text":null,"width":490,"height":361,"mime_type":null,"sha256":"d2730f5563f896d9498bbc4ba399178f0b44c2fc9e4522ecedf4f1733f7f09c5","phash":"e3c1847cec09f91b","classifier_tier":"clip","confidence":0.23480890691280365,"classification_evidence":["keyword:no_text_signal","clip:police_activity:0.23","gemini_skipped:budget_or_offline"],"is_stock_photo":false,"is_evidence":false,"evidence_reason":"default:no_evidence_signal","appearance_count":1}],"media_evidence":[],"victim_outcome":"died","motive":"خلاف مستمرّ بين عصابات","organized_crime":true,"family_dispute":false,"community_context":null,"sources":[{"url":"https://www.arab48.com/محليات/أخبار-محلية/2026/02/18/إصابة-شاب-بجراح-حرجة-برصاص-الشرطة-في-كابول","discovery_source":"arab48","actual_publisher":"Arab48","source_name":"Arab48","language":"ar","published_at":"2026-02-18T17:49:17","confidence_score":0.8,"paywalled":false,"body_extracted":true},{"url":"https://www.arab48.com/محليات/دراسات-وتقارير/2026/02/19/جريمة-القتل-المزدوجة-في-حيفا-نزيف-متواصل-ووالدة-مكلومة-تفقد-ابنيها-بالمكان-ذاته--لا-طعم-لحياتي-","discovery_source":"arab48","actual_publisher":"Arab48","source_name":"Arab48","language":"ar","published_at":"2026-02-19T19:27:55","confidence_score":0.9,"paywalled":false,"body_extracted":true},{"url":"https://www.ynet.co.il/news/article/b1irgkxubx","discovery_source":"ynet","actual_publisher":"Ynet","source_name":"Ynet","language":"he","published_at":"2026-02-18T08:00:00","confidence_score":0.9,"paywalled":false,"body_extracted":true},{"url":"https://news.walla.co.il/item/3818250","discovery_source":"walla","actual_publisher":"Walla News","source_name":"Walla News","language":"he","published_at":"2026-02-20T14:13:00","confidence_score":0.8,"paywalled":false,"body_extracted":true}],"conflicts":{"num_victims":{"arab48":2}},"flags":["district:field_conflict","num_victims:victim_count_conflict","suspect_status:status_regression","needs_tier_1","needs_tier_3","needs_tier_2"],"confidence":{"case_identity":0.85,"victim_identity":0.417,"timeline":0.333,"legal_status":0.3,"location_detail":0.333,"media":0.05},"confidence_score":0.85,"tier_coverage":{"tier_1":[],"tier_2":["Arab48","Arab48"],"tier_3":[],"untiered":[]},"timeline":[{"date":"2026-02-18","event":"Incident occurred","confidence":"high"},{"date":"2026-02-18","event":"Reported in Arab48","confidence":"high","source_url":"https://www.arab48.com/محليات/أخبار-محلية/2026/02/18/إصابة-شاب-بجراح-حرجة-برصاص-الشرطة-في-كابول"},{"date":"2026-02-19","event":"Reported in Arab48","confidence":"high","source_url":"https://www.arab48.com/محليات/دراسات-وتقارير/2026/02/19/جريمة-القتل-المزدوجة-في-حيفا-نزيف-متواصل-ووالدة-مكلومة-تفقد-ابنيها-بالمكان-ذاته--لا-طعم-لحياتي-"}],"motive_translations":null,"arrest_location_translations":null,"dropped_invalid_sources":[],"rejected_unrelated_articles":[],"reconciliation_provenance":[{"merged_from_url":"https://www.ynet.co.il/news/article/b1irgkxubx","reason":"name_match","jaro_score":0.893},{"merged_from_url":"https://news.walla.co.il/item/3818250","reason":"name_match","jaro_score":0.893}],"case_narrative_ar":"قُتل سهيل أبو جبل، البالغ من العمر 26 عامًا، في 18 فبراير 2026، إثر تعرضه لإطلاق نار في متجر بمدينة حيفا. أُعلن عن وفاته في موقع الجريمة. ولم تعلن الشرطة عن اعتقال مشتبه بهم في هذه الجريمة المزدوجة.","case_narrative_he":"סוהיל אבו ג'בל, בן 26, נרצח ב-18 בפברואר 2026 מירי במינימרקט בשכונת חליסה בחיפה. מותו נקבע בזירה. המשטרה לא דיווחה על מעצר חשודים בפרשה זו.","case_narrative_en":"Suhail Abu Jabal, 26, was killed on February 18, 2026, in a shooting at a minimarket in Haifa. He was pronounced dead at the scene. Police have not announced any arrests in connection with this double homicide.","review_status":"flagged_for_review","pipeline_run_id":"canonical_2026-01-01_2026-05-15","enrichment_passes":0,"_pipeline_run_id":"canonical_2026-01-01_2026-05-15","run_id":"canonical","case_index":52}